Questa/Vending_FSM.v
`timescale 1ns/1ps

module vending_top #(
  parameter [5:0] INIT_PRICE0 = 6'd6,   // $30
  parameter [5:0] INIT_PRICE1 = 6'd8,   // $40
  parameter [5:0] INIT_PRICE2 = 6'd10,  // $50
  parameter [5:0] INIT_PRICE3 = 6'd12,  // $60
  parameter [3:0] INIT_INV    = 4'd8,   // product inventory 
  parameter [5:0] INIT_BANK   = 6'd10   // $50 
)(
  input  wire        clk,
  input  wire        rst_n,

  // External inputs
  input  wire        coin_valid,         // (1)
  input  wire [1:0]  coin_type,          // (2)
  input  wire        sel_valid,          // (1)
  input  wire [1:0]  sel_id,             // (2)
  input  wire        cancel,             // (1)

  // External outputs
  output reg         dispense_valid,     // (1) 1-cycle pulse in VEND
  output reg  [1:0]  dispense_id,        // (2)
  output reg         change_pulse,        // (1) 1-cycle pulse per returned coin
  output reg  [1:0]  change_type,         // (2)
  output reg  [1:0]  status_code,        // (2) 00=OK,01=BUSY,10=ERROR
  output reg  [1:0]  err_code            // (2) 00=none,01=soldout,10=nochange
);

  localparam [2:0]
    S_IDLE      = 3'd0,
    S_ACCEPT    = 3'd1,
    S_CHECK     = 3'd2,
    S_VEND      = 3'd3,
    S_MAKE_CHG  = 3'd4,
    S_WAIT_CHG  = 3'd5,
    S_RETURN    = 3'd6,
    S_ERROR     = 3'd7;

  localparam [2:0]
    C_IDLE = 3'd0,
    C_TRY25= 3'd1,
    C_TRY10= 3'd2,
    C_TRY5 = 3'd3,
    C_DONE = 3'd4;

  localparam [1:0]
    ERR_NONE     = 2'd0,
    ERR_SOLDOUT  = 2'd1,
    ERR_NOCHANGE = 2'd2;


  reg [2:0] state, next_state;
  reg [2:0] cstate, cnext_state;

  reg [5:0] balance;        // (6) in $5 units
  reg [5:0] change_bank;    // (6) in $5 units 
  reg [5:0] change_rem;     // (6) remaining change to return
  reg [1:0] sel_reg;        // (2) latched selection

  reg [5:0] price [0:3];    // (6) 
  reg [3:0] inv   [0:3];    // (4) 

  integer i;


  wire [5:0] price_sel = price[sel_reg];
  wire [3:0] inv_sel   = inv[sel_reg];

  wire soldout     = (inv_sel == 0);
  wire enough      = (balance >= price_sel);
  wire rem_zero    = (change_rem == 0);
  wire bank_enough = (change_bank >= change_rem);

  // Coin value decode 
  wire [5:0] coin_value =
      (coin_type==2'b00) ? 6'd1 :
      (coin_type==2'b01) ? 6'd2 :
      (coin_type==2'b10) ? 6'd5 : 6'd0;

  // Change can-subtract conditions 
  wire can25 = (change_rem >= 6'd5) && (change_bank >= 6'd5);
  wire can10 = (change_rem >= 6'd2) && (change_bank >= 6'd2);
  wire can5  = (change_rem >= 6'd1) && (change_bank >= 6'd1);

  reg do_add_coin;
  reg do_latch_sel;
  reg do_dec_inv;
  reg do_compute_change;      // change_rem = balance - price_sel
  reg do_load_rem_from_bal;   // change_rem = balance
  reg do_clear_balance;
  reg change_start_pulse;     // starts change FSM 
  reg chg_sub_pulse;          // 1-cycle subtract event
  reg [1:0] chg_denom;        // 10/01/00
  reg chg_done_pulse;         // 1-cycle done indicator from change FSM


  always @(negedge clk or negedge rst_n) begin
    if (!rst_n) state <= S_IDLE;
    else        state <= next_state;
  end

  always @(negedge clk or negedge rst_n) begin
    if (!rst_n) cstate <= C_IDLE;
    else        cstate <= cnext_state;
  end


  always @(*) begin
    next_state = state;
    case (state)
      S_IDLE: begin
        if (coin_valid)      next_state = S_ACCEPT;
        else if (sel_valid)  next_state = S_CHECK;
        else if (cancel)     next_state = S_RETURN;
      end
      S_ACCEPT: begin
        if (sel_valid)       next_state = S_CHECK;
        else if (cancel)     next_state = S_RETURN;
        else                 next_state = S_ACCEPT;
      end
      S_CHECK: begin
        if (soldout)         next_state = S_ERROR;
        else if (!enough)    next_state = S_ACCEPT;
        else                 next_state = S_VEND;
      end
      S_VEND: begin
        next_state = S_MAKE_CHG;
      end
      S_MAKE_CHG: begin
        if (rem_zero)          next_state = S_IDLE;
        else if (!bank_enough) next_state = S_ERROR;
        else                   next_state = S_WAIT_CHG;
      end
      S_WAIT_CHG: begin
        if (chg_done_pulse)  next_state = S_IDLE;
        else                 next_state = S_WAIT_CHG;
      end
      S_RETURN: begin
        if (balance == 0)    next_state = S_IDLE;
        else                 next_state = S_WAIT_CHG;
      end
      S_ERROR: begin
        if (cancel)          next_state = S_IDLE;
        else                 next_state = S_ERROR;
      end
      default: next_state = S_IDLE;
    endcase
  end

  
  always @(*) begin
    cnext_state = cstate;
    case (cstate)
      C_IDLE:   if (change_start_pulse) cnext_state = C_TRY25;
      C_TRY25:  if (can25)              cnext_state = C_TRY25;
                else                    cnext_state = C_TRY10;
      C_TRY10:  if (can10)              cnext_state = C_TRY10;
                else                    cnext_state = C_TRY5;
      C_TRY5:   if (can5)               cnext_state = C_TRY5;
                else                    cnext_state = C_DONE;
      C_DONE:   cnext_state = C_IDLE;
      default:  cnext_state = C_IDLE;
    endcase
  end

  
  always @(negedge clk or negedge rst_n) begin
    if (!rst_n) begin
      do_add_coin          <= 1'b0;
      do_latch_sel         <= 1'b0;
      do_dec_inv           <= 1'b0;
      do_compute_change    <= 1'b0;
      do_load_rem_from_bal <= 1'b0;
      do_clear_balance     <= 1'b0;
      change_start_pulse   <= 1'b0;

      chg_sub_pulse        <= 1'b0;
      chg_denom            <= 2'b00;
      chg_done_pulse       <= 1'b0;

      dispense_valid       <= 1'b0;
      dispense_id          <= 2'b00;
      change_pulse         <= 1'b0;
      change_type          <= 2'b00;
      status_code          <= 2'b00;
      err_code             <= ERR_NONE;
    end else begin
      do_add_coin          <= 1'b0;
      do_latch_sel         <= 1'b0;
      do_dec_inv           <= 1'b0;
      do_compute_change    <= 1'b0;
      do_load_rem_from_bal <= 1'b0;
      do_clear_balance     <= 1'b0;
      change_start_pulse   <= 1'b0;

      chg_sub_pulse        <= 1'b0;
      chg_denom            <= 2'b00;
      chg_done_pulse       <= 1'b0;

      dispense_valid       <= 1'b0;
      dispense_id          <= sel_reg;
      change_pulse         <= 1'b0;
      change_type          <= 2'b00;

      status_code          <= 2'b01; // BUSY
      err_code             <= ERR_NONE;

      // Main FSM controls
      case (state)
        S_IDLE: begin
          status_code <= 2'b00;
          if (coin_valid)  do_add_coin  <= 1'b1;
          if (sel_valid)   do_latch_sel <= 1'b1;
        end
        S_ACCEPT: begin
          if (coin_valid)  do_add_coin  <= 1'b1;
          if (sel_valid)   do_latch_sel <= 1'b1;
        end
        S_CHECK: begin
          if (soldout) begin
            status_code <= 2'b10;
            err_code    <= ERR_SOLDOUT;
          end
        end
        S_VEND: begin
          dispense_valid    <= 1'b1;
          dispense_id       <= sel_reg;
          do_dec_inv        <= 1'b1;
          do_compute_change <= 1'b1;
        end
        S_MAKE_CHG: begin
          if (rem_zero) begin
            do_clear_balance <= 1'b1;
            status_code      <= 2'b00;
          end else if (!bank_enough) begin
            status_code <= 2'b10;
            err_code    <= ERR_NOCHANGE;
          end else begin
            change_start_pulse <= 1'b1;
          end
        end
        S_RETURN: begin
          if (balance != 0) begin
            do_load_rem_from_bal <= 1'b1;
            change_start_pulse   <= 1'b1;
          end else begin
            status_code <= 2'b00;
          end
        end
        S_ERROR: begin
          status_code <= 2'b10;
        end
        default: ;
      endcase

      
      case (cstate)
        C_TRY25: if (can25) begin
          chg_sub_pulse <= 1'b1;
          chg_denom     <= 2'b10;
          change_pulse  <= 1'b1;
          change_type   <= 2'b10;
        end
        C_TRY10: if (can10) begin
          chg_sub_pulse <= 1'b1;
          chg_denom     <= 2'b01;
          change_pulse  <= 1'b1;
          change_type   <= 2'b01;
        end
        C_TRY5:  if (can5) begin
          chg_sub_pulse <= 1'b1;
          chg_denom     <= 2'b00;
          change_pulse  <= 1'b1;
          change_type   <= 2'b00;
        end
        C_DONE: begin
          chg_done_pulse <= 1'b1; 
          status_code    <= 2'b00;
          do_clear_balance <= 1'b1;
        end
        default: ;
      endcase
    end
  end


  always @(posedge clk or negedge rst_n) begin
    if (!rst_n) begin
      balance     <= 6'd0;
      change_bank <= INIT_BANK;
      change_rem  <= 6'd0;
      sel_reg     <= 2'd0;

      price[0] <= INIT_PRICE0;
      price[1] <= INIT_PRICE1;
      price[2] <= INIT_PRICE2;
      price[3] <= INIT_PRICE3;

      for (i=0;i<4;i=i+1) inv[i] <= INIT_INV;
    end else begin
      if (do_add_coin) balance <= balance + coin_value;
      if (do_latch_sel) sel_reg <= sel_id;

      if (do_dec_inv) begin
        if (inv[sel_reg] != 0) inv[sel_reg] <= inv[sel_reg] - 1'b1;
      end

      if (do_compute_change) change_rem <= balance - price_sel;
      if (do_load_rem_from_bal) change_rem <= balance;

      if (chg_sub_pulse) begin
        case (chg_denom)
          2'b10: begin change_rem <= change_rem - 6'd5; change_bank <= change_bank - 6'd5; end
          2'b01: begin change_rem <= change_rem - 6'd2; change_bank <= change_bank - 6'd2; end
          2'b00: begin change_rem <= change_rem - 6'd1; change_bank <= change_bank - 6'd1; end
          default: ;
        endcase
      end

      if (do_clear_balance) begin
        balance    <= 6'd0;
        change_rem <= 6'd0;
      end
    end
  end

endmodule

Synthesis/Vending_FSM_tb.v

`timescale 1ns/1ps

module tb_vending_two_phase;

  reg clk;
  reg rst_n;

  reg coin_valid;
  reg [1:0] coin_type;
  reg sel_valid;
  reg [1:0] sel_id;
  reg cancel;

  wire dispense_valid;
  wire [1:0] dispense_id;
  wire change_pulse;
  wire [1:0] change_type;
  wire [1:0] status_code;
  wire [1:0] err_code;

  vending_top dut (
    .clk(clk), .rst_n(rst_n),
    .coin_valid(coin_valid), .coin_type(coin_type),
    .sel_valid(sel_valid), .sel_id(sel_id),
    .cancel(cancel),
    .dispense_valid(dispense_valid), .dispense_id(dispense_id),
    .change_pulse(change_pulse), .change_type(change_type),
    .status_code(status_code), .err_code(err_code)
  );

  // 100MHz clock
  initial clk = 0;
  always #5 clk = ~clk;

  
  task insert_coin(input [1:0] t);
    begin
      @(posedge clk);
      coin_type  <= t;
      coin_valid <= 1'b1;
      @(posedge clk);
      coin_valid <= 1'b0;
      coin_type  <= 2'b00;
    end
  endtask

  task select_item(input [1:0] id);
    begin
      @(posedge clk);
      sel_id    <= id;
      sel_valid <= 1'b1;
      @(posedge clk);
      sel_valid <= 1'b0;
      sel_id    <= 2'b00;
    end
  endtask

  task do_cancel;
    begin
      @(posedge clk);
      cancel <= 1'b1;
      @(posedge clk);
      cancel <= 1'b0;
    end
  endtask

  // Wave dump
  initial begin
    $dumpfile("vending_pre.vcd");
    $dumpvars(0, tb_vending_two_phase);
  end

  // Monitors
  always @(negedge clk) begin
    if (dispense_valid) $display("[%0t] DISPENSE id=%0d", $time, dispense_id);
    if (change_pulse)   $display("[%0t] CHANGE type=%b", $time, change_type);
    if (err_code!=0)    $display("[%0t] ERROR code=%0d", $time, err_code);
  end

  initial begin
    coin_valid=0; coin_type=0;
    sel_valid=0;  sel_id=0;
    cancel=0;

    rst_n=0;
    repeat(4) @(posedge clk);
    rst_n=1;

    // Case 1: Exact pay, vend item0 (price0=6 units=$30): $25 + $5
    insert_coin(2'b10);
    insert_coin(2'b00);
    select_item(2'd0);
    repeat(20) @(posedge clk);

    // Case 2: Overpay, vend item1 (price1=8 units=$40): $25+$25 => change $10
    insert_coin(2'b10);
    insert_coin(2'b10);
    select_item(2'd1);
    repeat(30) @(posedge clk);

    // Case 3: Insufficient then add more, vend item2 (price2=10 units=$50)
    insert_coin(2'b10);
    select_item(2'd2);
    insert_coin(2'b10);
    repeat(30) @(posedge clk);

    // Case 4: Cancel and refund
    insert_coin(2'b10);
    insert_coin(2'b00);
    do_cancel();
    repeat(30) @(posedge clk);

    // Case 5: Soldout (force inv[3]=0) then select item3
    dut.inv[3] = 0;
    select_item(2'd3);
    repeat(10) @(posedge clk);

    // Case 6: No-change (force bank=0) with overpay => error
    dut.change_bank = 0;
    insert_coin(2'b10);
    insert_coin(2'b10);
    select_item(2'd0);
    repeat(20) @(posedge clk);

    $finish;
  end

endmodule

Questa/vending_pre.vcd
$date
	Wed Feb 25 18:24:58 2026
$end
$version
	QuestaSim Version 2023.2
$end
$timescale
	1ps
$end

$scope module tb_vending_two_phase $end
$var reg 1 ! clk $end
$var reg 1 " rst_n $end
$var reg 1 # coin_valid $end
$var reg 2 $ coin_type [1:0] $end
$var reg 1 % sel_valid $end
$var reg 2 & sel_id [1:0] $end
$var reg 1 ' cancel $end
$var wire 1 ( dispense_valid $end
$var wire 1 ) dispense_id [1] $end
$var wire 1 * dispense_id [0] $end
$var wire 1 + change_pulse $end
$var wire 1 , change_type [1] $end
$var wire 1 - change_type [0] $end
$var wire 1 . status_code [1] $end
$var wire 1 / status_code [0] $end
$var wire 1 0 err_code [1] $end
$var wire 1 1 err_code [0] $end

$scope task insert_coin $end
$var reg 2 2 t [1:0] $end
$upscope $end

$scope task select_item $end
$var reg 2 3 id [1:0] $end
$upscope $end

$scope task do_cancel $end
$upscope $end

$scope module dut $end
$var parameter 6 4 INIT_PRICE0 $end
$var parameter 6 5 INIT_PRICE1 $end
$var parameter 6 6 INIT_PRICE2 $end
$var parameter 6 7 INIT_PRICE3 $end
$var parameter 4 8 INIT_INV $end
$var parameter 6 9 INIT_BANK $end
$var parameter 3 : S_IDLE $end
$var parameter 3 ; S_ACCEPT $end
$var parameter 3 < S_CHECK $end
$var parameter 3 = S_VEND $end
$var parameter 3 > S_MAKE_CHG $end
$var parameter 3 ? S_WAIT_CHG $end
$var parameter 3 @ S_RETURN $end
$var parameter 3 A S_ERROR $end
$var parameter 3 B C_IDLE $end
$var parameter 3 C C_TRY25 $end
$var parameter 3 D C_TRY10 $end
$var parameter 3 E C_TRY5 $end
$var parameter 3 F C_DONE $end
$var parameter 2 G ERR_NONE $end
$var parameter 2 H ERR_SOLDOUT $end
$var parameter 2 I ERR_NOCHANGE $end
$var wire 1 J clk $end
$var wire 1 K rst_n $end
$var wire 1 L coin_valid $end
$var wire 1 M coin_type [1] $end
$var wire 1 N coin_type [0] $end
$var wire 1 O sel_valid $end
$var wire 1 P sel_id [1] $end
$var wire 1 Q sel_id [0] $end
$var wire 1 R cancel $end
$var reg 1 S dispense_valid $end
$var reg 2 T dispense_id [1:0] $end
$var reg 1 U change_pulse $end
$var reg 2 V change_type [1:0] $end
$var reg 2 W status_code [1:0] $end
$var reg 2 X err_code [1:0] $end
$var reg 3 Y state [2:0] $end
$var reg 3 Z next_state [2:0] $end
$var reg 3 [ cstate [2:0] $end
$var reg 3 \ cnext_state [2:0] $end
$var reg 6 ] balance [5:0] $end
$var reg 6 ^ change_bank [5:0] $end
$var reg 6 _ change_rem [5:0] $end
$var reg 2 ` sel_reg [1:0] $end
$var integer 32 a i $end
$var wire 1 b price_sel [5] $end
$var wire 1 c price_sel [4] $end
$var wire 1 d price_sel [3] $end
$var wire 1 e price_sel [2] $end
$var wire 1 f price_sel [1] $end
$var wire 1 g price_sel [0] $end
$var wire 1 h inv_sel [3] $end
$var wire 1 i inv_sel [2] $end
$var wire 1 j inv_sel [1] $end
$var wire 1 k inv_sel [0] $end
$var wire 1 l soldout $end
$var wire 1 m enough $end
$var wire 1 n rem_zero $end
$var wire 1 o bank_enough $end
$var wire 1 p coin_value [5] $end
$var wire 1 q coin_value [4] $end
$var wire 1 r coin_value [3] $end
$var wire 1 s coin_value [2] $end
$var wire 1 t coin_value [1] $end
$var wire 1 u coin_value [0] $end
$var wire 1 v can25 $end
$var wire 1 w can10 $end
$var wire 1 x can5 $end
$var reg 1 y do_add_coin $end
$var reg 1 z do_latch_sel $end
$var reg 1 { do_dec_inv $end
$var reg 1 | do_compute_change $end
$var reg 1 } do_load_rem_from_bal $end
$var reg 1 ~ do_clear_balance $end
$var reg 1 !! change_start_pulse $end
$var reg 1 "! chg_sub_pulse $end
$var reg 2 #! chg_denom [1:0] $end
$var reg 1 $! chg_done_pulse $end
$upscope $end
$upscope $end
$enddefinitions $end
#0
$dumpvars
0!
0"
0#
b0 $
0%
b0 &
0'
0S
b0 T
0U
b0 V
b0 W
b0 X
b0 Y
b0 Z
b0 [
b0 \
b0 ]
b1010 ^
b0 _
b0 `
0y
0z
0{
0|
0}
0~
0!!
0"!
b0 #!
0$!
bx 2
bx 3
b110 4
b1000 5
b1010 6
b1100 7
b1000 8
b1010 9
b0 :
b1 ;
b10 <
b11 =
b100 >
b101 ?
b110 @
b111 A
b0 B
b1 C
b10 D
b11 E
b100 F
b0 G
b1 H
b10 I
b100 a
0(
0*
0)
0+
0-
0,
0/
0.
01
00
0g
1f
1e
0d
0c
0b
0k
0j
0i
1h
0l
0m
1n
1o
1u
0t
0s
0r
0q
0p
0v
0w
0x
0R
0Q
0P
0O
0N
0M
0L
0K
0J
$end
#5000
1!
1J
b0 a
b1 a
b10 a
b11 a
b100 a
#10000
0!
0J
#15000
1!
1J
#20000
0!
0J
#25000
1!
1J
#30000
0!
0J
#35000
1!
1J
1"
b10 2
1K
#40000
0!
0J
b1 W
b0 W
#45000
1!
1J
b10 $
1#
1M
1s
1L
b1 Z
#50000
0!
0J
b1 Y
b1 W
b0 W
1y
#55000
1!
1J
b0 2
b101 ]
0#
b0 $
0M
0s
0L
#60000
0!
0J
0y
b1 W
1/
#65000
1!
1J
1#
1L
#70000
0!
0J
1y
#75000
1!
1J
b0 3
b110 ]
0#
1m
0L
#80000
0!
0J
0y
#85000
1!
1J
1%
1O
b10 Z
#90000
0!
0J
b10 Y
1z
b11 Z
#95000
1!
1J
0%
0O
b10 Z
b11 Z
#100000
0!
0J
b11 Y
0z
b100 Z
#105000
1!
1J
#110000
0!
0J
b100 Y
1S
1{
1|
1(
b0 Z
#115000
1!
1J
1k
1j
1i
0h
#120000
0!
0J
b0 Y
0{
0|
0S
1~
b0 W
0(
0/
#125000
1!
1J
b0 ]
0m
#130000
0!
0J
0~
b1 W
b0 W
#135000
1!
1J
#140000
0!
0J
b1 W
b0 W
#145000
1!
1J
#150000
0!
0J
b1 W
b0 W
#155000
1!
1J
#160000
0!
0J
b1 W
b0 W
#165000
1!
1J
#170000
0!
0J
b1 W
b0 W
#175000
1!
1J
#180000
0!
0J
b1 W
b0 W
#185000
1!
1J
#190000
0!
0J
b1 W
b0 W
#195000
1!
1J
#200000
0!
0J
b1 W
b0 W
#205000
1!
1J
#210000
0!
0J
b1 W
b0 W
#215000
1!
1J
#220000
0!
0J
b1 W
b0 W
#225000
1!
1J
#230000
0!
0J
b1 W
b0 W
#235000
1!
1J
#240000
0!
0J
b1 W
b0 W
#245000
1!
1J
#250000
0!
0J
b1 W
b0 W
#255000
1!
1J
#260000
0!
0J
b1 W
b0 W
#265000
1!
1J
#270000
0!
0J
b1 W
b0 W
#275000
1!
1J
#280000
0!
0J
b1 W
b0 W
#285000
1!
1J
#290000
0!
0J
b1 W
b0 W
#295000
1!
1J
b10 2
#300000
0!
0J
b1 W
b0 W
#305000
1!
1J
b10 $
1#
1M
1s
1L
b1 Z
#310000
0!
0J
b1 Y
b1 W
b0 W
1y
#315000
1!
1J
b101 ]
0#
b0 $
0M
0s
0L
#320000
0!
0J
0y
b1 W
1/
#325000
1!
1J
b10 $
1#
1M
1s
1L
#330000
0!
0J
1y
#335000
1!
1J
b1 3
b1010 ]
0#
b0 $
0M
0s
1m
0L
#340000
0!
0J
0y
#345000
1!
1J
b1 &
1%
1Q
1O
b10 Z
#350000
0!
0J
b10 Y
1z
b11 Z
#355000
1!
1J
b1 `
0%
b0 &
0Q
0f
0e
1d
0k
0j
0i
1h
0O
b10 Z
b11 Z
#360000
0!
0J
b11 Y
0z
b1 T
1*
b100 Z
#365000
1!
1J
#370000
0!
0J
b100 Y
1S
1{
1|
1(
b0 Z
#375000
1!
1J
b10 _
1k
1j
1i
0h
1x
1w
0n
b100 Z
b101 Z
#380000
0!
0J
b101 Y
0{
0|
0S
1!!
0(
b1 \
#385000
1!
1J
#390000
0!
0J
b1 [
0!!
b10 \
#395000
1!
1J
#400000
0!
0J
b10 [
#405000
1!
1J
#410000
0!
0J
1"!
b1 #!
1U
b1 V
1+
1-
#415000
1!
1J
b0 _
b1000 ^
0x
0w
1n
b11 \
#420000
0!
0J
b11 [
0"!
b0 #!
0U
b0 V
0+
0-
b100 \
#425000
1!
1J
#430000
0!
0J
b100 [
b0 \
#435000
1!
1J
#440000
0!
0J
b0 [
1$!
b0 W
1~
0/
b0 Z
#445000
1!
1J
b0 ]
0m
b101 Z
b0 Z
#450000
0!
0J
b0 Y
0~
0$!
b1 W
1/
#455000
1!
1J
#460000
0!
0J
b0 W
0/
#465000
1!
1J
#470000
0!
0J
b1 W
b0 W
#475000
1!
1J
#480000
0!
0J
b1 W
b0 W
#485000
1!
1J
#490000
0!
0J
b1 W
b0 W
#495000
1!
1J
#500000
0!
0J
b1 W
b0 W
#505000
1!
1J
#510000
0!
0J
b1 W
b0 W
#515000
1!
1J
#520000
0!
0J
b1 W
b0 W
#525000
1!
1J
#530000
0!
0J
b1 W
b0 W
#535000
1!
1J
#540000
0!
0J
b1 W
b0 W
#545000
1!
1J
#550000
0!
0J
b1 W
b0 W
#555000
1!
1J
#560000
0!
0J
b1 W
b0 W
#565000
1!
1J
#570000
0!
0J
b1 W
b0 W
#575000
1!
1J
#580000
0!
0J
b1 W
b0 W
#585000
1!
1J
#590000
0!
0J
b1 W
b0 W
#595000
1!
1J
#600000
0!
0J
b1 W
b0 W
#605000
1!
1J
#610000
0!
0J
b1 W
b0 W
#615000
1!
1J
#620000
0!
0J
b1 W
b0 W
#625000
1!
1J
#630000
0!
0J
b1 W
b0 W
#635000
1!
1J
#640000
0!
0J
b1 W
b0 W
#645000
1!
1J
#650000
0!
0J
b1 W
b0 W
#655000
1!
1J
#660000
0!
0J
b1 W
b0 W
#665000
1!
1J
b10 $
1#
1M
1s
1L
b1 Z
#670000
0!
0J
b1 Y
b1 W
b0 W
1y
#675000
1!
1J
b10 3
b101 ]
0#
b0 $
0M
0s
0L
#680000
0!
0J
0y
b1 W
1/
#685000
1!
1J
b10 &
1%
1P
1O
b10 Z
#690000
0!
0J
b10 Y
1z
b1 Z
#695000
1!
1J
b10 `
0%
b0 &
0P
1f
0k
0j
0i
1h
0O
b10 Z
b1 Z
#700000
0!
0J
b1 Y
0z
b10 T
0*
1)
#705000
1!
1J
b10 $
1#
1M
1s
1L
#710000
0!
0J
1y
#715000
1!
1J
b1010 ]
0#
b0 $
0M
0s
1m
0L
#720000
0!
0J
0y
