Synthesis/vending_datapath.v
`timescale 1ns/1ps

module vending_datapath #(
    parameter [5:0] INIT_PRICE0 = 6'd6,   // $30
    parameter [5:0] INIT_PRICE1 = 6'd8,   // $40
    parameter [5:0] INIT_PRICE2 = 6'd10,  // $50
    parameter [5:0] INIT_PRICE3 = 6'd12,  // $60
    parameter [3:0] INIT_INV    = 4'd8,   //inventory
    parameter [5:0] INIT_BANK   = 6'd10   // $50 -> 10 units
)(
    input  wire       clkb,
    input  wire       rst_n,

    // external-like datapath inputs
    input  wire       coin_valid,
    input  wire [1:0] coin_type,
    input  wire [1:0] sel_id,

    // control from FSM
    input  wire       do_add_coin,
    input  wire       do_latch_sel,
    input  wire       do_dec_inv,
    input  wire       do_compute_change,
    input  wire       do_load_rem_from_bal,
    input  wire       do_clear_balance,
    input  wire       chg_sub_pulse,
    input  wire [1:0] chg_denom,

    // status back to FSM
    output wire       soldout,
    output wire       enough,
    output wire       rem_zero,
    output wire       bank_enough,
    output wire       balance_zero,
    output wire       can25,
    output wire       can10,
    output wire       can5,

    // observation outputs
    output wire [1:0] sel_reg_out,
    output wire [5:0] balance_out,
    output wire [5:0] change_rem_out
);

    reg [5:0] balance;
    reg [5:0] change_bank;
    reg [5:0] change_rem;
    reg [1:0] sel_reg;

    reg [5:0] price [0:3];
    reg [3:0] inv   [0:3];

    integer i;

    wire [5:0] price_sel = price[sel_reg];
    wire [3:0] inv_sel   = inv[sel_reg];

    // decoder
    wire [5:0] coin_value =
        (coin_type == 2'b00) ? 6'd1 :
        (coin_type == 2'b01) ? 6'd2 :
        (coin_type == 2'b10) ? 6'd5 : 6'd0;

    assign soldout      = (inv_sel == 0);
    assign enough       = (balance >= price_sel);
    assign rem_zero     = (change_rem == 0);
    assign bank_enough  = (change_bank >= change_rem);
    assign balance_zero = (balance == 0);

    assign can25 = (change_rem >= 6'd5) && (change_bank >= 6'd5);
    assign can10 = (change_rem >= 6'd2) && (change_bank >= 6'd2);
    assign can5  = (change_rem >= 6'd1) && (change_bank >= 6'd1);

    assign sel_reg_out    = sel_reg;
    assign balance_out    = balance;
    assign change_rem_out = change_rem;

    always @(negedge clkb) begin
        if (!rst_n) begin
            balance     <= 6'd0;
            change_bank <= INIT_BANK;
            change_rem  <= 6'd0;
            sel_reg     <= 2'd0;

            price[0] <= INIT_PRICE0;
            price[1] <= INIT_PRICE1;
            price[2] <= INIT_PRICE2;
            price[3] <= INIT_PRICE3;

            for (i = 0; i < 4; i = i + 1)
                inv[i] <= INIT_INV;
        end else begin
            if (do_add_coin && coin_valid)
                balance <= balance + coin_value;

            if (do_latch_sel)
                sel_reg <= sel_id;

            if (do_dec_inv && inv[sel_reg] != 0)
                inv[sel_reg] <= inv[sel_reg] - 1'b1;

            if (do_compute_change)
                change_rem <= balance - price_sel;

            if (do_load_rem_from_bal)
                change_rem <= balance;

            if (chg_sub_pulse) begin
                case (chg_denom)
                    2'b10: begin
                        change_rem  <= change_rem - 6'd5;
                        change_bank <= change_bank - 6'd5;
                    end
                    2'b01: begin
                        change_rem  <= change_rem - 6'd2;
                        change_bank <= change_bank - 6'd2;
                    end
                    2'b00: begin
                        change_rem  <= change_rem - 6'd1;
                        change_bank <= change_bank - 6'd1;
                    end
                    default: ;
                endcase
            end

            if (do_clear_balance) begin
                balance    <= 6'd0;
                change_rem <= 6'd0;
            end
        end
    end

endmodule

Questa/vending_fsm.v
`timescale 1ns/1ps

module vending_fsm(
    input  wire       clka,
    input  wire       rst_n,

    // external inputs observed by controller
    input  wire       coin_valid,
    input  wire       sel_valid,
    input  wire       cancel,

    // datapath flags
    input  wire       soldout,
    input  wire       enough,
    input  wire       rem_zero,
    input  wire       bank_enough,
    input  wire       balance_zero,
    input  wire       can25,
    input  wire       can10,
    input  wire       can5,

    // latched selected id from datapath
    input  wire [1:0] sel_reg_id,

    // control to datapath
    output reg        do_add_coin,
    output reg        do_latch_sel,
    output reg        do_dec_inv,
    output reg        do_compute_change,
    output reg        do_load_rem_from_bal,
    output reg        do_clear_balance,
    output reg        chg_sub_pulse,
    output reg  [1:0] chg_denom,
    output reg        change_start_pulse,

    // external outputs
    output reg        dispense_valid,
    output reg  [1:0] dispense_id,
    output reg        change_pulse,
    output reg  [1:0] change_type,
    output reg  [1:0] status_code,
    output reg  [1:0] err_code
);
    // main_FSM
    localparam [2:0]
        S_IDLE      = 3'd0,
        S_ACCEPT    = 3'd1,
        S_CHECK     = 3'd2,
        S_VEND      = 3'd3,
        S_MAKE_CHG  = 3'd4,
        S_WAIT_CHG  = 3'd5,
        S_RETURN    = 3'd6,
        S_ERROR     = 3'd7;

    // change_FSM
    localparam [2:0] 
        C_IDLE  = 3'd0,
        C_TRY25 = 3'd1,// greedy change return
        C_TRY10 = 3'd2,
        C_TRY5  = 3'd3,
        C_DONE  = 3'd4;

    localparam [1:0]
        ERR_NONE     = 2'd0,
        ERR_SOLDOUT  = 2'd1,
        ERR_NOCHANGE = 2'd2;

    reg [2:0] state, next_state; //main_FSM
    reg [2:0] cstate, cnext_state; //change_FSM
    reg       chg_done_pulse;

    // state registers
    always @(negedge clka) begin
        if (!rst_n)
            state <= S_IDLE;
        else
            state <= next_state;
    end

    always @(negedge clka) begin
        if (!rst_n)
            cstate <= C_IDLE;
        else
            cstate <= cnext_state;
    end

    // main_FSM next state 
    always @(*) begin
        next_state = state;
        case (state)
            S_IDLE: begin
                if (coin_valid)      next_state = S_ACCEPT;
                else if (sel_valid)  next_state = S_CHECK;
                else if (cancel)     next_state = S_RETURN;
            end

            S_ACCEPT: begin
                if (sel_valid)       next_state = S_CHECK;
                else if (cancel)     next_state = S_RETURN;
                else                 next_state = S_ACCEPT;
            end

            S_CHECK: begin
                if (soldout)         next_state = S_ERROR;
                else if (!enough)    next_state = S_ACCEPT;
                else                 next_state = S_VEND;
            end

            S_VEND:
                next_state = S_MAKE_CHG;

            S_MAKE_CHG: begin
                if (rem_zero)          next_state = S_IDLE;
                else if (!bank_enough) next_state = S_ERROR;
                else                   next_state = S_WAIT_CHG;
            end

            S_WAIT_CHG: begin
                if (chg_done_pulse) next_state = S_IDLE;
                else                next_state = S_WAIT_CHG;
            end

            S_RETURN: begin
                if (balance_zero) next_state = S_IDLE;
                else              next_state = S_WAIT_CHG;
            end

            S_ERROR: begin
                if (cancel) next_state = S_IDLE;
                else        next_state = S_ERROR;
            end

            default:
                next_state = S_IDLE;
        endcase
    end

    // change_FSM next state 
    always @(*) begin
        cnext_state = cstate;
        case (cstate)
            C_IDLE: begin
                if (change_start_pulse)
                    cnext_state = C_TRY25;
            end

            C_TRY25: begin
                if (rem_zero)
                    cnext_state = C_DONE;
                else if (can25)
                    cnext_state = C_TRY25;
                else
                    cnext_state = C_TRY10;
            end

            C_TRY10: begin
                if (rem_zero)
                    cnext_state = C_DONE;
                else if (can10)
                    cnext_state = C_TRY10;
                else
                    cnext_state = C_TRY5;
            end

            C_TRY5: begin
                if (rem_zero)
                    cnext_state = C_DONE;
                else if (can5)
                    cnext_state = C_TRY5;
                else
                    cnext_state = C_DONE;
            end

            C_DONE:
                cnext_state = C_IDLE;

            default:
                cnext_state = C_IDLE;
        endcase
    end

    // output/control register 
    always @(negedge clka) begin
        if (!rst_n) begin
            do_add_coin          <= 1'b0;
            do_latch_sel         <= 1'b0;
            do_dec_inv           <= 1'b0;
            do_compute_change    <= 1'b0;
            do_load_rem_from_bal <= 1'b0;
            do_clear_balance     <= 1'b0;
            chg_sub_pulse        <= 1'b0;
            chg_denom            <= 2'b00;
            change_start_pulse   <= 1'b0;
            chg_done_pulse       <= 1'b0;

            dispense_valid       <= 1'b0;
            dispense_id          <= 2'b00;
            change_pulse         <= 1'b0;
            change_type          <= 2'b00;
            status_code          <= 2'b00;
            err_code             <= ERR_NONE;
        end else begin
            // defaults each cycle
            do_add_coin          <= 1'b0;
            do_latch_sel         <= 1'b0;
            do_dec_inv           <= 1'b0;
            do_compute_change    <= 1'b0;
            do_load_rem_from_bal <= 1'b0;
            do_clear_balance     <= 1'b0;
            chg_sub_pulse        <= 1'b0;
            chg_denom            <= 2'b00;
            change_start_pulse   <= 1'b0;
            chg_done_pulse       <= 1'b0;

            dispense_valid       <= 1'b0;
            dispense_id          <= sel_reg_id;
            change_pulse         <= 1'b0;
            change_type          <= 2'b00;

            status_code          <= 2'b01; // BUSY default
            err_code             <= ERR_NONE;

            // main_FSM outputs
            case (state)
                S_IDLE: begin
                    status_code <= 2'b00; 
                    if (coin_valid)
                        do_add_coin <= 1'b1;
                    if (sel_valid)
                        do_latch_sel <= 1'b1;
                end

                S_ACCEPT: begin
                    if (coin_valid)
                        do_add_coin <= 1'b1;
                    if (sel_valid)
                        do_latch_sel <= 1'b1;
                end

                S_CHECK: begin
                    if (soldout) begin
                        status_code <= 2'b10;
                        err_code    <= ERR_SOLDOUT;
                    end
                end

                S_VEND: begin
                    dispense_valid    <= 1'b1;
                    dispense_id       <= sel_reg_id;
                    do_dec_inv        <= 1'b1;
                    do_compute_change <= 1'b1;
                end

                S_MAKE_CHG: begin
                    if (rem_zero) begin
                        do_clear_balance <= 1'b1;
                        status_code      <= 2'b00;
                    end else if (!bank_enough) begin
                        status_code <= 2'b10;
                        err_code    <= ERR_NOCHANGE;
                    end else begin
                        change_start_pulse <= 1'b1;
                    end
                end

                S_RETURN: begin
                    if (!balance_zero) begin
                        do_load_rem_from_bal <= 1'b1;
                        change_start_pulse   <= 1'b1;
                    end else begin
                        status_code <= 2'b00;
                    end
                end

                S_WAIT_CHG: begin
                    status_code <= 2'b01; // BUSY
                end

                S_ERROR: begin
                    status_code <= 2'b10;
                end
            endcase

            // change_FSM outputs
            case (cstate)
                C_TRY25: begin
                    if (can25) begin
                        chg_sub_pulse <= 1'b1;
                        chg_denom     <= 2'b10;
                        change_pulse  <= 1'b1;
                        change_type   <= 2'b10;
                    end
                end

                C_TRY10: begin
                    if (can10) begin
                        chg_sub_pulse <= 1'b1;
                        chg_denom     <= 2'b01;
                        change_pulse  <= 1'b1;
                        change_type   <= 2'b01;
                    end
                end

                C_TRY5: begin
                    if (can5) begin
                        chg_sub_pulse <= 1'b1;
                        chg_denom     <= 2'b00;
                        change_pulse  <= 1'b1;
                        change_type   <= 2'b00;
                    end
                end

                C_DONE: begin
                    chg_done_pulse   <= 1'b1;
                    do_clear_balance <= 1'b1;
                    status_code      <= 2'b00;
                end
            endcase
        end
    end

endmodule

Questa/vending_top.v
`timescale 1ns/1ps

module vending_top(
    input  wire       clka,
    input  wire       clkb,
    input  wire       rst_n,
    input  wire       coin_valid,
    input  wire [1:0] coin_type,
    input  wire       sel_valid,
    input  wire [1:0] sel_id,
    input  wire       cancel,

    output wire       dispense_valid,
    output wire [1:0] dispense_id,
    output wire       change_pulse,
    output wire [1:0] change_type,
    output wire [1:0] status_code,
    output wire [1:0] err_code
);

    wire do_add_coin, do_latch_sel, do_dec_inv;
    wire do_compute_change, do_load_rem_from_bal, do_clear_balance;
    wire chg_sub_pulse, change_start_pulse;
    wire [1:0] chg_denom;

    wire soldout, enough, rem_zero, bank_enough, balance_zero;
    wire can25, can10, can5;
    wire [1:0] sel_reg_out;
    wire [5:0] balance_out, change_rem_out;

    vending_fsm u_fsm (
        .clka(clka),
        .rst_n(rst_n),
        .coin_valid(coin_valid),
        .sel_valid(sel_valid),
        .cancel(cancel),

        .soldout(soldout),
        .enough(enough),
        .rem_zero(rem_zero),
        .bank_enough(bank_enough),
        .balance_zero(balance_zero),
        .can25(can25),
        .can10(can10),
        .can5(can5),

        .sel_reg_id(sel_reg_out),

        .do_add_coin(do_add_coin),
        .do_latch_sel(do_latch_sel),
        .do_dec_inv(do_dec_inv),
        .do_compute_change(do_compute_change),
        .do_load_rem_from_bal(do_load_rem_from_bal),
        .do_clear_balance(do_clear_balance),
        .chg_sub_pulse(chg_sub_pulse),
        .chg_denom(chg_denom),
        .change_start_pulse(change_start_pulse),

        .dispense_valid(dispense_valid),
        .dispense_id(dispense_id),
        .change_pulse(change_pulse),
        .change_type(change_type),
        .status_code(status_code),
        .err_code(err_code)
    );

    vending_datapath u_datapath (
        .clkb(clkb),
        .rst_n(rst_n),

        .coin_valid(coin_valid),
        .coin_type(coin_type),
        .sel_id(sel_id),

        .do_add_coin(do_add_coin),
        .do_latch_sel(do_latch_sel),
        .do_dec_inv(do_dec_inv),
        .do_compute_change(do_compute_change),
        .do_load_rem_from_bal(do_load_rem_from_bal),
        .do_clear_balance(do_clear_balance),
        .chg_sub_pulse(chg_sub_pulse),
        .chg_denom(chg_denom),

        .soldout(soldout),
        .enough(enough),
        .rem_zero(rem_zero),
        .bank_enough(bank_enough),
        .balance_zero(balance_zero),
        .can25(can25),
        .can10(can10),
        .can5(can5),

        .sel_reg_out(sel_reg_out),
        .balance_out(balance_out),
        .change_rem_out(change_rem_out)
    );

endmodule

Questa/vending_FSM_tb.v
`timescale 1ns/1ps

module tb_vending_two_phase;

    reg clka;
    reg clkb;
    reg rst_n;

    reg coin_valid;
    reg [1:0] coin_type;
    reg sel_valid;
    reg [1:0] sel_id;
    reg cancel;

    wire dispense_valid;
    wire [1:0] dispense_id;
    wire change_pulse;
    wire [1:0] change_type;
    wire [1:0] status_code;
    wire [1:0] err_code;

    vending_top dut (
        .clka(clka),
        .clkb(clkb),
        .rst_n(rst_n),
        .coin_valid(coin_valid),
        .coin_type(coin_type),
        .sel_valid(sel_valid),
        .sel_id(sel_id),
        .cancel(cancel),
        .dispense_valid(dispense_valid),
        .dispense_id(dispense_id),
        .change_pulse(change_pulse),
        .change_type(change_type),
        .status_code(status_code),
        .err_code(err_code)
    );

    initial begin
        clka = 1'b0;
        clkb = 1'b0;
        forever begin
            #5;
            clka = 1'b1;
            #10;
            clka = 1'b0;

            #5;
            clkb = 1'b1;
            #10;
            clkb = 1'b0;
        end
    end

    task insert_coin(input [1:0] t);
        begin
            @(posedge clka);
            coin_type  <= t;
            coin_valid <= 1'b1;
            @(posedge clka);
            coin_valid <= 1'b0;
            coin_type  <= 2'b00;
        end
    endtask

    task select_item(input [1:0] id);
        begin
            @(posedge clka);
            sel_id    <= id;
            sel_valid <= 1'b1;
            @(posedge clka);
            sel_valid <= 1'b0;
            sel_id    <= 2'b00;
        end
    endtask

    task do_cancel;
        begin
            @(posedge clka);
            cancel <= 1'b1;
            @(posedge clka);
            cancel <= 1'b0;
        end
    endtask

    initial begin
        $dumpfile("vending_top_pre.vcd");
        $dumpvars(0, tb_vending_two_phase);
    end

    always @(negedge clka) begin
        if (dispense_valid)
            $display("[%0t] DISPENSE id=%0d", $time, dispense_id);

        if (change_pulse)
            $display("[%0t] CHANGE type=%b", $time, change_type);

        if (err_code != 0)
            $display("[%0t] ERROR code=%0d", $time, err_code);
    end

    initial begin
        coin_valid = 0;
        coin_type  = 0;
        sel_valid  = 0;
        sel_id     = 0;
        cancel     = 0;

        rst_n = 0;
        repeat(4) @(posedge clka);
        rst_n = 1;

        // Case 1: exact pay item0 ($25 + $5 = $30)
        insert_coin(2'b10);
        insert_coin(2'b00);
        select_item(2'd0);
        repeat(20) @(posedge clka);

        // Case 2: overpay item1 ($25 + $25, price = $40)
        insert_coin(2'b10);
        insert_coin(2'b10);
        select_item(2'd1);
        repeat(30) @(posedge clka);

        // Case 3: insufficient then add more for item2 ($50)
        insert_coin(2'b10);
        select_item(2'd2);
        insert_coin(2'b10);
        select_item(2'd2);
        repeat(30) @(posedge clka);

        // Case 4: cancel/refund
        insert_coin(2'b10);
        insert_coin(2'b00);
        do_cancel();
        repeat(30) @(posedge clka);

        $finish;
    end

endmodule

Questa/vending_top_pre.vcd
$date
	Sun Apr 12 00:48:18 2026
$end
$version
	QuestaSim Version 2023.2
$end
$timescale
	1ps
$end

$scope module tb_vending_two_phase $end
$var reg 1 ! clka $end
$var reg 1 " clkb $end
$var reg 1 # rst_n $end
$var reg 1 $ coin_valid $end
$var reg 2 % coin_type [1:0] $end
$var reg 1 & sel_valid $end
$var reg 2 ' sel_id [1:0] $end
$var reg 1 ( cancel $end
$var wire 1 ) dispense_valid $end
$var wire 1 * dispense_id [1] $end
$var wire 1 + dispense_id [0] $end
$var wire 1 , change_pulse $end
$var wire 1 - change_type [1] $end
$var wire 1 . change_type [0] $end
$var wire 1 / status_code [1] $end
$var wire 1 0 status_code [0] $end
$var wire 1 1 err_code [1] $end
$var wire 1 2 err_code [0] $end

$scope task insert_coin $end
$var reg 2 3 t [1:0] $end
$upscope $end

$scope task select_item $end
$var reg 2 4 id [1:0] $end
$upscope $end

$scope task do_cancel $end
$upscope $end

$scope module dut $end
$var wire 1 5 clka $end
$var wire 1 6 clkb $end
$var wire 1 7 rst_n $end
$var wire 1 8 coin_valid $end
$var wire 1 9 coin_type [1] $end
$var wire 1 : coin_type [0] $end
$var wire 1 ; sel_valid $end
$var wire 1 < sel_id [1] $end
$var wire 1 = sel_id [0] $end
$var wire 1 > cancel $end
$var wire 1 ) dispense_valid $end
$var wire 1 * dispense_id [1] $end
$var wire 1 + dispense_id [0] $end
$var wire 1 , change_pulse $end
$var wire 1 - change_type [1] $end
$var wire 1 . change_type [0] $end
$var wire 1 / status_code [1] $end
$var wire 1 0 status_code [0] $end
$var wire 1 1 err_code [1] $end
$var wire 1 2 err_code [0] $end
$var wire 1 ? do_add_coin $end
$var wire 1 @ do_latch_sel $end
$var wire 1 A do_dec_inv $end
$var wire 1 B do_compute_change $end
$var wire 1 C do_load_rem_from_bal $end
$var wire 1 D do_clear_balance $end
$var wire 1 E chg_sub_pulse $end
$var wire 1 F change_start_pulse $end
$var wire 1 G chg_denom [1] $end
$var wire 1 H chg_denom [0] $end
$var wire 1 I soldout $end
$var wire 1 J enough $end
$var wire 1 K rem_zero $end
$var wire 1 L bank_enough $end
$var wire 1 M balance_zero $end
$var wire 1 N can25 $end
$var wire 1 O can10 $end
$var wire 1 P can5 $end
$var wire 1 Q sel_reg_out [1] $end
$var wire 1 R sel_reg_out [0] $end
$var wire 1 S balance_out [5] $end
$var wire 1 T balance_out [4] $end
$var wire 1 U balance_out [3] $end
$var wire 1 V balance_out [2] $end
$var wire 1 W balance_out [1] $end
$var wire 1 X balance_out [0] $end
$var wire 1 Y change_rem_out [5] $end
$var wire 1 Z change_rem_out [4] $end
$var wire 1 [ change_rem_out [3] $end
$var wire 1 \ change_rem_out [2] $end
$var wire 1 ] change_rem_out [1] $end
$var wire 1 ^ change_rem_out [0] $end

$scope module u_fsm $end
$var parameter 3 _ S_IDLE $end
$var parameter 3 ` S_ACCEPT $end
$var parameter 3 a S_CHECK $end
$var parameter 3 b S_VEND $end
$var parameter 3 c S_MAKE_CHG $end
$var parameter 3 d S_WAIT_CHG $end
$var parameter 3 e S_RETURN $end
$var parameter 3 f S_ERROR $end
$var parameter 3 g C_IDLE $end
$var parameter 3 h C_TRY25 $end
$var parameter 3 i C_TRY10 $end
$var parameter 3 j C_TRY5 $end
$var parameter 3 k C_DONE $end
$var parameter 2 l ERR_NONE $end
$var parameter 2 m ERR_SOLDOUT $end
$var parameter 2 n ERR_NOCHANGE $end
$var wire 1 5 clka $end
$var wire 1 7 rst_n $end
$var wire 1 8 coin_valid $end
$var wire 1 ; sel_valid $end
$var wire 1 > cancel $end
$var wire 1 I soldout $end
$var wire 1 J enough $end
$var wire 1 K rem_zero $end
$var wire 1 L bank_enough $end
$var wire 1 M balance_zero $end
$var wire 1 N can25 $end
$var wire 1 O can10 $end
$var wire 1 P can5 $end
$var wire 1 Q sel_reg_id [1] $end
$var wire 1 R sel_reg_id [0] $end
$var reg 1 o do_add_coin $end
$var reg 1 p do_latch_sel $end
$var reg 1 q do_dec_inv $end
$var reg 1 r do_compute_change $end
$var reg 1 s do_load_rem_from_bal $end
$var reg 1 t do_clear_balance $end
$var reg 1 u chg_sub_pulse $end
$var reg 2 v chg_denom [1:0] $end
$var reg 1 w change_start_pulse $end
$var reg 1 x dispense_valid $end
$var reg 2 y dispense_id [1:0] $end
$var reg 1 z change_pulse $end
$var reg 2 { change_type [1:0] $end
$var reg 2 | status_code [1:0] $end
$var reg 2 } err_code [1:0] $end
$var reg 3 ~ state [2:0] $end
$var reg 3 !! next_state [2:0] $end
$var reg 3 "! cstate [2:0] $end
$var reg 3 #! cnext_state [2:0] $end
$var reg 1 $! chg_done_pulse $end
$upscope $end

$scope module u_datapath $end
$var parameter 6 %! INIT_PRICE0 $end
$var parameter 6 &! INIT_PRICE1 $end
$var parameter 6 '! INIT_PRICE2 $end
$var parameter 6 (! INIT_PRICE3 $end
$var parameter 4 )! INIT_INV $end
$var parameter 6 *! INIT_BANK $end
$var wire 1 6 clkb $end
$var wire 1 7 rst_n $end
$var wire 1 8 coin_valid $end
$var wire 1 9 coin_type [1] $end
$var wire 1 : coin_type [0] $end
$var wire 1 < sel_id [1] $end
$var wire 1 = sel_id [0] $end
$var wire 1 ? do_add_coin $end
$var wire 1 @ do_latch_sel $end
$var wire 1 A do_dec_inv $end
$var wire 1 B do_compute_change $end
$var wire 1 C do_load_rem_from_bal $end
$var wire 1 D do_clear_balance $end
$var wire 1 E chg_sub_pulse $end
$var wire 1 G chg_denom [1] $end
$var wire 1 H chg_denom [0] $end
$var wire 1 I soldout $end
$var wire 1 J enough $end
$var wire 1 K rem_zero $end
$var wire 1 L bank_enough $end
$var wire 1 M balance_zero $end
$var wire 1 N can25 $end
$var wire 1 O can10 $end
$var wire 1 P can5 $end
$var wire 1 Q sel_reg_out [1] $end
$var wire 1 R sel_reg_out [0] $end
$var wire 1 S balance_out [5] $end
$var wire 1 T balance_out [4] $end
$var wire 1 U balance_out [3] $end
$var wire 1 V balance_out [2] $end
$var wire 1 W balance_out [1] $end
$var wire 1 X balance_out [0] $end
$var wire 1 Y change_rem_out [5] $end
$var wire 1 Z change_rem_out [4] $end
$var wire 1 [ change_rem_out [3] $end
$var wire 1 \ change_rem_out [2] $end
$var wire 1 ] change_rem_out [1] $end
$var wire 1 ^ change_rem_out [0] $end
$var reg 6 +! balance [5:0] $end
$var reg 6 ,! change_bank [5:0] $end
$var reg 6 -! change_rem [5:0] $end
$var reg 2 .! sel_reg [1:0] $end
$var integer 32 /! i $end
$var wire 1 0! price_sel [5] $end
$var wire 1 1! price_sel [4] $end
$var wire 1 2! price_sel [3] $end
$var wire 1 3! price_sel [2] $end
$var wire 1 4! price_sel [1] $end
$var wire 1 5! price_sel [0] $end
$var wire 1 6! inv_sel [3] $end
$var wire 1 7! inv_sel [2] $end
$var wire 1 8! inv_sel [1] $end
$var wire 1 9! inv_sel [0] $end
$var wire 1 :! coin_value [5] $end
$var wire 1 ;! coin_value [4] $end
$var wire 1 <! coin_value [3] $end
$var wire 1 =! coin_value [2] $end
$var wire 1 >! coin_value [1] $end
$var wire 1 ?! coin_value [0] $end
$upscope $end
$upscope $end
$upscope $end
$enddefinitions $end
#0
$dumpvars
0!
0"
0#
0$
b0 %
0&
b0 '
0(
0o
0p
0q
0r
0s
0t
0u
b0 v
0w
0x
b0 y
0z
b0 {
b0 |
b0 }
b0 ~
b0 !!
b0 "!
b0 #!
0$!
b0 +!
b1010 ,!
b0 -!
b0 .!
bx 3
bx 4
b0 _
b1 `
b10 a
b11 b
b100 c
b101 d
b110 e
b111 f
b0 g
b1 h
b10 i
b11 j
b100 k
b0 l
b1 m
b10 n
b110 %!
b1000 &!
b1010 '!
b1100 (!
b1000 )!
b1010 *!
b100 /!
0)
0+
0*
0,
0.
0-
00
0/
02
01
0?
0@
0A
0B
0C
0D
0E
0F
0H
0G
0I
0J
1K
1L
1M
0N
0O
0P
0R
0Q
0X
0W
0V
0U
0T
0S
0^
0]
0\
0[
0Z
0Y
05!
14!
13!
02!
01!
00!
09!
08!
07!
16!
1?!
0>!
0=!
0<!
0;!
0:!
0>
0=
0<
0;
0:
09
08
07
06
05
$end
#5000
1!
15
#15000
0!
05
#20000
1"
16
#30000
0"
06
b0 /!
b1 /!
b10 /!
b11 /!
b100 /!
#35000
1!
15
#45000
0!
05
#50000
1"
16
#60000
0"
06
#65000
1!
15
#75000
0!
05
#80000
1"
16
#90000
0"
06
#95000
1!
15
1#
b10 3
17
#105000
0!
05
b1 |
b0 |
#110000
1"
16
#120000
0"
06
#125000
1!
15
b10 %
1$
19
1=!
18
b1 !!
#135000
0!
05
b1 ~
b1 |
b0 |
1o
1?
#140000
1"
16
#150000
0"
06
b101 +!
1X
1V
0M
#155000
1!
15
b0 3
0$
b0 %
09
0=!
08
#165000
0!
05
0o
b1 |
0?
10
#170000
1"
16
#180000
0"
06
#185000
1!
15
1$
18
#195000
0!
05
1o
1?
#200000
1"
16
#210000
0"
06
b110 +!
0X
1W
1J
#215000
1!
15
b0 4
0$
08
#225000
0!
05
0o
0?
#230000
1"
16
#240000
0"
06
#245000
1!
15
1&
1;
b10 !!
#255000
0!
05
b10 ~
1p
1@
b11 !!
#260000
1"
16
#270000
0"
06
#275000
1!
15
0&
0;
b10 !!
b11 !!
#285000
0!
05
b11 ~
0p
0@
b100 !!
#290000
1"
16
#300000
0"
06
#305000
1!
15
#315000
0!
05
b100 ~
1x
1q
1r
1)
1A
1B
b0 !!
#320000
1"
16
#330000
0"
06
19!
18!
17!
06!
#335000
1!
15
#345000
0!
05
b0 ~
0q
0r
0x
1t
b0 |
0A
0B
0)
1D
00
#350000
1"
16
#360000
0"
06
b0 +!
0W
0V
1M
0J
#365000
1!
15
#375000
0!
05
0t
b1 |
b0 |
0D
#380000
1"
16
#390000
0"
06
#395000
1!
15
#405000
0!
05
b1 |
b0 |
#410000
1"
16
#420000
0"
06
#425000
1!
15
#435000
0!
05
b1 |
b0 |
#440000
1"
16
#450000
0"
06
#455000
1!
15
#465000
0!
05
b1 |
b0 |
#470000
1"
16
#480000
0"
06
#485000
1!
15
#495000
0!
05
b1 |
b0 |
#500000
1"
16
#510000
0"
06
#515000
1!
15
#525000
0!
05
b1 |
b0 |
#530000
1"
16
#540000
0"
06
#545000
1!
15
#555000
0!
05
b1 |
b0 |
#560000
1"
16
#570000
0"
06
#575000
1!
15
#585000
0!
05
b1 |
b0 |
#590000
1"
16
#600000
0"
06
#605000
1!
15
#615000
0!
05
b1 |
b0 |
#620000
1"
16
#630000
0"
06
#635000
1!
15
#645000
0!
05
b1 |
b0 |
#650000
1"
16
#660000
0"
06
#665000
1!
15
#675000
0!
05
b1 |
b0 |
#680000
1"
16
#690000
0"
06
#695000
1!
15
#705000
0!
05
b1 |
b0 |
#710000
1"
16
#720000
0"
06
#725000
1!
15
#735000
0!
05
b1 |
b0 |
#740000
1"
16
#750000
0"
06
#755000
1!
15
#765000
0!
05
b1 |
b0 |
#770000
1"
16
#780000
0"
06
#785000
1!
15
#795000
0!
05
b1 |
b0 |
#800000
1"
16
#810000
0"
06
#815000
1!
15
#825000
0!
05
b1 |
b0 |
#830000
1"
16
#840000
0"
06
#845000
1!
15
#855000
0!
05
b1 |
b0 |
#860000
1"
16
#870000
0"
06
#875000
1!
15
b10 3
#885000
0!
05
b1 |
b0 |
#890000
1"
16
#900000
0"
06
#905000
1!
15
b10 %
1$
19
1=!
18
b1 !!
#915000
0!
05
b1 ~
b1 |
b0 |
1o
1?
#920000
1"
16
#930000
0"
06
b101 +!
1X
1V
0M
#935000
1!
15
0$
b0 %
09
0=!
08
#945000
0!
05
0o
b1 |
0?
10
#950000
1"
16
#960000
0"
06
#965000
1!
15
b10 %
1$
19
1=!
18
#975000
0!
05
1o
1?
#980000
1"
16
#990000
0"
06
b1010 +!
0X
1W
0V
1U
1J
#995000
1!
15
b1 4
0$
b0 %
09
0=!
08
#1005000
0!
05
0o
0?
#1010000
1"
16
#1020000
0"
06
#1025000
1!
15
b1 '
1&
1=
1;
b10 !!
#1035000
0!
05
b10 ~
1p
1@
b11 !!
#1040000
1"
16
#1050000
0"
06
b1 .!
1R
04!
03!
12!
09!
08!
07!
16!
#1055000
1!
15
0&
b0 '
0=
0;
b10 !!
b11 !!
#1065000
0!
05
b11 ~
0p
b1 y
0@
1+
b100 !!
#1070000
1"
16
#1080000
0"
06
#1085000
1!
15
#1095000
0!
05
b100 ~
1x
1q
1r
1)
1A
1B
b0 !!
#1100000
1"
16
#1110000
0"
06
b10 -!
1]
19!
18!
17!
06!
1P
1O
0K
b100 !!
b101 !!
#1115000
1!
15
#1125000
0!
05
b101 ~
0q
0r
0x
1w
0A
0B
0)
1F
b1 #!
#1130000
1"
16
#1140000
0"
06
#1145000
1!
15
#1155000
0!
05
b1 "!
0w
0F
b10 #!
#1160000
1"
16
#1170000
0"
06
#1175000
1!
15
#1185000
0!
05
b10 "!
#1190000
1"
16
#1200000
0"
06
#1205000
1!
15
#1215000
0!
05
1u
b1 v
1z
b1 {
1E
1,
1.
1H
#1220000
1"
16
#1230000
0"
06
b0 -!
b1000 ,!
0]
0P
0O
1K
b100 #!
#1235000
1!
15
#1245000
0!
05
b100 "!
0u
b0 v
0z
b0 {
0E
0,
0.
0H
b0 #!
#1250000
1"
16
#1260000
0"
06
#1265000
1!
15
#1275000
0!
05
b0 "!
1$!
1t
b0 |
1D
00
b0 !!
#1280000
1"
16
#1290000
0"
06
b0 +!
0W
0U
1M
0J
b101 !!
b0 !!
#1295000
1!
15
#1305000
0!
05
b0 ~
0t
0$!
b1 |
0D
10
#1310000
1"
16
#1320000
0"
06
#1325000
1!
15
#1335000
0!
05
b0 |
00
#1340000
1"
16
#1350000
0"
06
#1355000
1!
15
#1365000
0!
05
b1 |
b0 |
#1370000
1"
16
#1380000
0"
06
#1385000
1!
15
#1395000
0!
05
b1 |
b0 |
#1400000
1"
16
#1410000
0"
06
#1415000
1!
15
#1425000
0!
05
b1 |
b0 |
#1430000
1"
16
#1440000
0"
06
#1445000
1!
15
#1455000
0!
05
b1 |
b0 |
#1460000
1"
16
#1470000
0"
06
#1475000
1!
15
